aiorest_ws/__init__.py
aiorest_ws/abstract.py
aiorest_ws/app.py
aiorest_ws/command_line.py
aiorest_ws/decorators.py
aiorest_ws/endpoints.py
aiorest_ws/exceptions.py
aiorest_ws/log.py
aiorest_ws/parsers.py
aiorest_ws/renderers.py
aiorest_ws/request.py
aiorest_ws/routers.py
aiorest_ws/status.py
aiorest_ws/validators.py
aiorest_ws/views.py
aiorest_ws/wrappers.py
aiorest_ws/auth/__init__.py
aiorest_ws/auth/exceptions.py
aiorest_ws/auth/permissions.py
aiorest_ws/auth/token/__init__.py
aiorest_ws/auth/token/backends.py
aiorest_ws/auth/token/exceptions.py
aiorest_ws/auth/token/managers.py
aiorest_ws/auth/token/middlewares.py
aiorest_ws/auth/token/utils.py
aiorest_ws/auth/user/__init__.py
aiorest_ws/auth/user/abstractions.py
aiorest_ws/auth/user/exceptions.py
aiorest_ws/auth/user/models.py
aiorest_ws/auth/user/utils.py
aiorest_ws/conf/__init__.py
aiorest_ws/conf/global_settings.py
aiorest_ws/db/__init__.py
aiorest_ws/db/utils.py
aiorest_ws/db/backends/__init__.py
aiorest_ws/db/backends/sqlite3/__init__.py
aiorest_ws/db/backends/sqlite3/constants.py
aiorest_ws/db/backends/sqlite3/managers.py
aiorest_ws/db/orm/__init__.py
aiorest_ws/db/orm/abstract.py
aiorest_ws/db/orm/exceptions.py
aiorest_ws/db/orm/fields.py
aiorest_ws/db/orm/relations.py
aiorest_ws/db/orm/serializers.py
aiorest_ws/db/orm/validators.py
aiorest_ws/db/orm/django/__init__.py
aiorest_ws/db/orm/django/compat.py
aiorest_ws/db/orm/django/field_mapping.py
aiorest_ws/db/orm/django/fields.py
aiorest_ws/db/orm/django/model_meta.py
aiorest_ws/db/orm/django/relations.py
aiorest_ws/db/orm/django/serializers.py
aiorest_ws/db/orm/django/validators.py
aiorest_ws/db/orm/sqlalchemy/__init__.py
aiorest_ws/db/orm/sqlalchemy/exceptions.py
aiorest_ws/db/orm/sqlalchemy/field_mapping.py
aiorest_ws/db/orm/sqlalchemy/fields.py
aiorest_ws/db/orm/sqlalchemy/mixins.py
aiorest_ws/db/orm/sqlalchemy/model_meta.py
aiorest_ws/db/orm/sqlalchemy/relations.py
aiorest_ws-1.1.1.dist-info/DESCRIPTION.rst
aiorest_ws-1.1.1.dist-info/METADATA
aiorest_ws-1.1.1.dist-info/RECORD
aiorest_ws-1.1.1.dist-info/WHEEL
aiorest_ws-1.1.1.dist-info/metadata.json
aiorest_ws-1.1.1.dist-info/top_level.txt
