Metadata-Version: 2.0
Name: aiorest-ws
Version: 1.1.1
Summary: REST framework with WebSockets support
Home-page: https://github.com/Relrin/aiorest-ws
Author: Valeryi Savich
Author-email: relrin78@gmail.com
License: BSD
Platform: any
Classifier: License :: OSI Approved :: BSD License
Classifier: Intended Audience :: Developers
Classifier: Programming Language :: Python
Classifier: Programming Language :: Python :: 3
Classifier: Programming Language :: Python :: 3.4
Classifier: Topic :: Internet :: WWW/HTTP
Requires-Dist: autobahn (==0.16.0)
